retinaface/__init__.py
retinaface/detector.py
retinaface/loader.py
retinaface/data/__init__.py
retinaface/data/config.py
retinaface/data/data_augment.py
retinaface/data/wider_face.py
retinaface/layers/__init__.py
retinaface/layers/modules/__init__.py
retinaface/layers/modules/multibox_loss.py
retinaface/models/__init__.py
retinaface/models/net.py
retinaface/models/retinaface.py
retinaface/utils/__init__.py
retinaface/utils/box_utils.py
retinaface/utils/timer.py
retinaface/utils/nms/__init__.py
retinaface/utils/nms/py_cpu_nms.py
Pytorch_detection-0.0.1.dist-info/LICENSE
Pytorch_detection-0.0.1.dist-info/METADATA
Pytorch_detection-0.0.1.dist-info/WHEEL
Pytorch_detection-0.0.1.dist-info/top_level.txt
Pytorch_detection-0.0.1.dist-info/RECORD
