Metadata-Version: 2.1
Name: Pytorch-detection
Version: 0.0.1
Summary: A small example package for face recognition
Home-page: https://github.com/hphuongdhsp/retinaface
Author: Hoang Phuong
Author-email: hphuongdhsp@gmail.com
License: MIT
Keywords: face detection,retinaface
Platform: UNKNOWN
Classifier: Programming Language :: Python :: 3
Classifier: License :: OSI Approved :: MIT License
Classifier: Operating System :: OS Independent
Requires-Python: >=3.6
Requires-Dist: albumentations
Requires-Dist: numpy
Requires-Dist: pillow
Requires-Dist: torch
Requires-Dist: torchvision
